{
  "placeholderImages": [
    {
      "id": "router",
      "description": "Mawacon Premium Router - FritzBox Fiber",
      "imageUrl": "/fritzbox-fiber.png",
      "imageHint": "router"
    },
    {
      "id": "repeater",
      "description": "Mawacon WiFi Booster",
      "imageUrl": "/wifi-boost.webp",
      "imageHint": "wifi repeater"
    },
    {
      "id": "tv_stick",
      "description": "waipu.tv 4K Streaming Stick",
      "imageUrl": "/waipu.png",
      "imageHint": "tv stick"
    },
    {
      "id": "customer_referral",
      "description": "Freunde werben Freunde",
      "imageUrl": "/friends.jpg",
      "imageHint": "friends referral"
    }
  ]
}